{
  "versionName": "1.0.3",
  "versionCode": 4,
  "minVersionCode": 1,
  "mandatory": false,
  "apkUrl": "https://github.com/brunaoperes/nero/releases/download/v1.0.3/gestor-pessoal-v1.0.3.apk",
  "apkSha256": "3785F302B6973819AC365A3DE7635D8D056663F10B3DBEA782F0A52771C0E18C",
  "changelog": [
    "🔧 URL CORRIGIDA - Agora funciona!",
    "✅ Usando raw.githubusercontent.com",
    "🔄 Verificação sem restrição de 24h",
    "🎯 Teste de atualização v1.0.2 → v1.0.3"
  ]
}
